{
	"name": "Cantarium Star Pad",
	"description": "...",
	"type": "MechPad",
	"mech": "cantarium-mech",
	"size": 4,
	"consumes": {
		"power": 1.3,
		"liquid": {
			"liquid": "cryofluid", 
			"amount": 1,
			"booster": false
		},
	},
	"category": "upgrade",
	"research": "scorch",
	"requirements": [
		{ "item": "titanium", "amount": 1000 },
		{ "item": "plastanium", "amount": 250 },
		{ "item": "graphite", "amount": 100 },
		{ "item": "thorium", "amount": 400 },
		{ "item": "silicon", "amount": 300 },
		{ "item": "gold", "amount": 110 }
	]
}
